{"1112351860382408709": {"tweet_id": "1112351860382408709", "replie_to": null, "quoting": "449525268529815552", "text": "Are you..... kidding me.?https://twitter.com/realDonaldTrump/status/449525268529815552 …", "user_id": "628050983", "user_screen_name": "carteroselett", "user_name": "carter oselett", "created_at": 1554040324000.0, "retweets": 5, "likes": 41, "replies": 1, "response_time": 0.0, "sentiment": 0.1027}, "1112406595634368513": {"tweet_id": "1112406595634368513", "replie_to": "1112351860382408709", "quoting": null, "text": "what the f u  c   k", "user_id": "1040222393392922624", "user_screen_name": "kellielounds", "user_name": "Kellie Lounds", "created_at": 1554053374000.0, "retweets": 0, "likes": 2, "replies": 1, "response_time": 13050.0, "sentiment": 0.0}, "1112409714330091521": {"tweet_id": "1112409714330091521", "replie_to": "1112406595634368513", "quoting": null, "text": "leader of the free world is spewing this s h i t to millions of followers?!", "user_id": "628050983", "user_screen_name": "carteroselett", "user_name": "carter oselett", "created_at": 1554054118000.0, "retweets": 0, "likes": 2, "replies": 0, "response_time": 744.0, "sentiment": 0.5562}}