{"1110612024399224835": {"tweet_id": "1110612024399224835", "replie_to": null, "quoting": "266036172122365952", "text": "jimin: queria ser um policial \njungkook: então me prenda \n\neu:https://twitter.com/ladygaga/status/266036172122365952 …", "user_id": "1015349262052405248", "user_screen_name": "voicevmin", "user_name": "ᅠ ᅠ", "created_at": 1553625515000.0, "retweets": 831, "likes": 1583, "replies": 5}, "1110757259922034689": {"tweet_id": "1110757259922034689", "replie_to": "1110612024399224835", "quoting": null, "text": "inesquecível", "user_id": "1015349262052405248", "user_screen_name": "voicevmin", "user_name": "ᅠ ᅠ", "created_at": 1553660142000.0, "retweets": 0, "likes": 1, "replies": 0}, "1110712090560479233": {"tweet_id": "1110712090560479233", "replie_to": "1110612024399224835", "quoting": null, "text": "Malmzlwkkaksknxksjd", "user_id": "1091488990149124098", "user_screen_name": "jjkluvxs", "user_name": "♡'s mina", "created_at": 1553649373000.0, "retweets": 0, "likes": 2, "replies": 0}, "1110911586129113088": {"tweet_id": "1110911586129113088", "replie_to": "1110612024399224835", "quoting": null, "text": "Não sei vcs mas, eu toda vez que vejo esse vídeo fico com vergonha alheia/ vontade de rir. Pq se perceber a reação dos meninos eles ficaram uma mistura de choque/sem graça/vergonha alheia e ficou um silencio constrangedor, tanto q quando o Jk percebe ele fica super envergonhado", "user_id": "906574602196996096", "user_screen_name": "CB_ianca", "user_name": "bia; 🏳️‍🌈 🦀", "created_at": 1553696936000.0, "retweets": 0, "likes": 1, "replies": 0}, "1110862481658966021": {"tweet_id": "1110862481658966021", "replie_to": "1110612024399224835", "quoting": null, "text": "licença encontrei o tuite antes da fama ok to aqui desde quando tudo isso era matopic.twitter.com/WLkUxQ1urB", "user_id": "1101254984891580416", "user_screen_name": "scarletprfct", "user_name": "ana. ♡", "created_at": 1553685229000.0, "retweets": 0, "likes": 0, "replies": 0}, "1110970281248604161": {"tweet_id": "1110970281248604161", "replie_to": "1110612024399224835", "quoting": null, "text": "Eu fico com vontade de me esconder de baixo da terra quando eu vejo esse video, muito Gay panic", "user_id": "244660468", "user_screen_name": "jakcq", "user_name": "JaqHild", "created_at": 1553710930000.0, "retweets": 0, "likes": 0, "replies": 0}}