{"1083535576060624898": {"tweet_id": "1083535576060624898", "replie_to": null, "quoting": "266036172122365952", "text": "reação dos naruteiros quando a kyuubi tomava conta do corpo do naruto durante a lutahttps://twitter.com/ladygaga/status/266036172122365952 …", "user_id": "1068713584425922560", "user_screen_name": "nvmikaze", "user_name": "minato", "created_at": 1547169987000.0, "retweets": 28, "likes": 78, "replies": 1}, "1083545631841533952": {"tweet_id": "1083545631841533952", "replie_to": "1083535576060624898", "quoting": null, "text": "eu amava???", "user_id": "1050510260723769344", "user_screen_name": "byakuganprincss", "user_name": "hinata hyuuga", "created_at": 1547172384000.0, "retweets": 0, "likes": 1, "replies": 0}}