{"1054944686794792962": {"tweet_id": "1054944686794792962", "replie_to": null, "quoting": "266036172122365952", "text": "me: \nmelissa:https://twitter.com/ladygaga/status/266036172122365952 …", "user_id": "1534536674", "user_screen_name": "chmbiies", "user_name": "bethany", "created_at": 1540353387000.0, "retweets": 0, "likes": 4, "replies": 1}, "1054944792113807360": {"tweet_id": "1054944792113807360", "replie_to": "1054944686794792962", "quoting": null, "text": "LMFAOOOOOOOYes", "user_id": "2259282966", "user_screen_name": "thumannn", "user_name": "cait", "created_at": 1540353413000.0, "retweets": 0, "likes": 1, "replies": 0}}