{"1111317840865435648": {"tweet_id": "1111317840865435648", "replie_to": null, "quoting": "1111295662920888320", "text": "It's evidence of a LOT more than those things. #antiscience #antiauthority #InternetCulturehttps://twitter.com/neiltyson/status/1111295662920888320 …", "user_id": "17668502", "user_screen_name": "IDoubtIt", "user_name": "Sharon A. Hill", "created_at": 1553793795000.0, "retweets": 2, "likes": 24, "replies": 4}, "1111333373040041984": {"tweet_id": "1111333373040041984", "replie_to": "1111317840865435648", "quoting": null, "text": "In your experience, are some of the flat-earthers doing it for internet notoriety (trolling), to some degree?", "user_id": "398811371", "user_screen_name": "shipwrek138", "user_name": "werewolf1777", "created_at": 1553797498000.0, "retweets": 0, "likes": 0, "replies": 1}, "1111378570893389825": {"tweet_id": "1111378570893389825", "replie_to": "1111317840865435648", "quoting": null, "text": "There's an antisemitic element as well, citing an international conspiracy of wealth Jewish people. Charming.", "user_id": "422958922", "user_screen_name": "OptimisticPaint", "user_name": "Exhaustonaut", "created_at": 1553808274000.0, "retweets": 0, "likes": 0, "replies": 0}, "1111334173086793728": {"tweet_id": "1111334173086793728", "replie_to": "1111333373040041984", "quoting": null, "text": "Sure. A few. They do like attention but it's not satire like it had been by some in the past. The antiauthority sentiment is the most obvious to me. Fits with today's widespread conspiracism and institutional distrust.", "user_id": "17668502", "user_screen_name": "IDoubtIt", "user_name": "Sharon A. Hill", "created_at": 1553797689000.0, "retweets": 0, "likes": 1, "replies": 0}}