{"1175028845046636544": {"tweet_id": "1175028845046636544", "replie_to": null, "quoting": "1175005540541509634", "text": "#LabourParty has a more responsible approach to #ClimateChange than the #GreenParty which has a slightly more extreme and fundamental one.https://twitter.com/jeremycorbyn/status/1175005540541509634 …", "user_id": "82857241", "user_screen_name": "DublinPJ", "user_name": "PJ", "created_at": 1568983682000.0, "retweets": 0, "likes": 0, "replies": 0, "sentiment": 0.3804, "response_time": 0.0}}