{"1172604893443567619": {"tweet_id": "1172604893443567619", "replie_to": null, "quoting": "1172598575257346049", "text": "E não é que pode ser bom...https://twitter.com/JamesGunn/status/1172598575257346049 …", "user_id": "979347821404057600", "user_screen_name": "MysteriousJudge", "user_name": "felipe", "created_at": 1568405767000.0, "retweets": 0, "likes": 2, "replies": 1, "sentiment": 0.0, "response_time": 0.0}, "1172607475956224000": {"tweet_id": "1172607475956224000", "replie_to": "1172604893443567619", "quoting": null, "text": "Ator bom não salva...", "user_id": "884087385776173056", "user_screen_name": "Priest_Hell", "user_name": "Priest #DeathStranding", "created_at": 1568406382000.0, "retweets": 0, "likes": 3, "replies": 1, "sentiment": 0.0, "response_time": 615.0}, "1172608451387805696": {"tweet_id": "1172608451387805696", "replie_to": "1172607475956224000", "quoting": null, "text": "Mas vai que por algum acaso do destino, o filme saia bom ahaha", "user_id": "979347821404057600", "user_screen_name": "MysteriousJudge", "user_name": "felipe", "created_at": 1568406615000.0, "retweets": 0, "likes": 1, "replies": 1, "sentiment": 0.0, "response_time": 233.0}, "1172613449031008257": {"tweet_id": "1172613449031008257", "replie_to": "1172608451387805696", "quoting": null, "text": "Espero", "user_id": "884087385776173056", "user_screen_name": "Priest_Hell", "user_name": "Priest #DeathStranding", "created_at": 1568407807000.0, "retweets": 0, "likes": 1, "replies": 0, "sentiment": 0.0, "response_time": 1192.0}}