{"1173297010704879618": {"tweet_id": "1173297010704879618", "replie_to": null, "quoting": "908396468821774336", "text": "2 anos atrás a população brasileira começou a descobrir o significado da palavra \"fibromialgia\".\nEu realmente acho que o cancelamento do show melhorou a nossa aceitação social. Já não ouço mais de ninguém que minha doença é coisa da minha cabeça.https://twitter.com/ladygaga/status/908396468821774336 …", "user_id": "18221776", "user_screen_name": "thainalima", "user_name": "cartomante paraguaia 🔮", "created_at": 1568570780000.0, "retweets": 1, "likes": 10, "replies": 1}, "1173433930374164480": {"tweet_id": "1173433930374164480", "replie_to": "1173297010704879618", "quoting": null, "text": "Acho que deu certa visibilidade a fibromialgia. Mas não tanto. Vivo de ouvir que eu TENHO QUE FAZER coisa X ou Y a todo custo, \"pq todo mundo faz, pq vc não?\". Quando falo da fibromialgia, aí tem quem diga \"tá fazendo corpo mole, olhaí Lady Gaga lotando shows e tu aí reclamando\".", "user_id": "38228088", "user_screen_name": "renataluna", "user_name": "Renata Luna", "created_at": 1568603425000.0, "retweets": 0, "likes": 0, "replies": 1}, "1173529831683870720": {"tweet_id": "1173529831683870720", "replie_to": "1173433930374164480", "quoting": null, "text": "Sério? Que bosta.\nSinto muito :/\nPra mim foi bem positivo, num geral.", "user_id": "18221776", "user_screen_name": "thainalima", "user_name": "cartomante paraguaia 🔮", "created_at": 1568626289000.0, "retweets": 0, "likes": 0, "replies": 0}}