{"1112488068504784897": {"tweet_id": "1112488068504784897", "replie_to": null, "quoting": "449525268529815552", "text": "meu deus eu sou mais inteligente que o presidente dos estados unidoshttps://twitter.com/realDonaldTrump/status/449525268529815552 …", "user_id": "3048285791", "user_screen_name": "nalumb", "user_name": "nalu #elenao", "created_at": 1554072799000.0, "retweets": 0, "likes": 22, "replies": 2}, "1112489697140449281": {"tweet_id": "1112489697140449281", "replie_to": "1112488068504784897", "quoting": null, "text": "quero saber  como eu não passei em med na federal desse jeito(???)", "user_id": "3048285791", "user_screen_name": "nalumb", "user_name": "nalu #elenao", "created_at": 1554073187000.0, "retweets": 0, "likes": 1, "replies": 0}, "1112494047355199489": {"tweet_id": "1112494047355199489", "replie_to": "1112488068504784897", "quoting": null, "text": "~aquela imagem do faustão feliz e triste ao fundo~", "user_id": "1255751892", "user_screen_name": "ChetDiniz", "user_name": "fê diniz #elenão", "created_at": 1554074224000.0, "retweets": 0, "likes": 0, "replies": 1}, "1112745282402426881": {"tweet_id": "1112745282402426881", "replie_to": "1112494047355199489", "quoting": null, "text": "um conceito.pic.twitter.com/SoaN5Insgf", "user_id": "3048285791", "user_screen_name": "nalumb", "user_name": "nalu #elenao", "created_at": 1554134123000.0, "retweets": 0, "likes": 1, "replies": 0}}