{"1065411624419409920": {"tweet_id": "1065411624419409920", "replie_to": null, "quoting": "1065400254151954432", "text": "You guys Trump is giving you a preview of what your uncle is going to be like at dinner tomorrow.https://twitter.com/realDonaldTrump/status/1065400254151954432 …", "user_id": "24889586", "user_screen_name": "AnandWrites", "user_name": "Anand Giridharadas", "created_at": 1542848900000.0, "retweets": 134, "likes": 1022, "replies": 16, "response_time": 0.0}, "1065413270281117702": {"tweet_id": "1065413270281117702", "replie_to": "1065411624419409920", "quoting": null, "text": "funny you should mention that, Anand:https://www.nytimes.com/2018/11/21/climate/happy-thanksgiving-weather-debate.html …", "user_id": "11179192", "user_screen_name": "jswatz", "user_name": "John Schwartz", "created_at": 1542849292000.0, "retweets": 1, "likes": 4, "replies": 1, "response_time": 392.0}, "1065412164280877056": {"tweet_id": "1065412164280877056", "replie_to": "1065411624419409920", "quoting": null, "text": "Not my uncle.\n\nMy dad.", "user_id": "1038890461769998336", "user_screen_name": "BogusDickBlack", "user_name": "Dick Black", "created_at": 1542849029000.0, "retweets": 0, "likes": 3, "replies": 1, "response_time": 129.0}, "1065420987750117376": {"tweet_id": "1065420987750117376", "replie_to": "1065411624419409920", "quoting": null, "text": "Why is it always the poor uncle who gets blamed?", "user_id": "25739434", "user_screen_name": "mcelarier", "user_name": "michelle celarier", "created_at": 1542851132000.0, "retweets": 0, "likes": 1, "replies": 0, "response_time": 2232.0}, "1065727343652560896": {"tweet_id": "1065727343652560896", "replie_to": "1065411624419409920", "quoting": null, "text": "warming? build a parasol/spaceport/industrial park at the Earth-Sun L1. cheaper in $$$ & liberty than losing carbon fuels. get blamed for the next ice age.https://www.astrobio.net/news-exclusive/how-earths-orbital-shift-shaped-the-sahara/ …", "user_id": "33220629", "user_screen_name": "aitepaeapaea", "user_name": "charles warren", "created_at": 1542924173000.0, "retweets": 0, "likes": 0, "replies": 0, "response_time": 75273.0}, "1065670606933426176": {"tweet_id": "1065670606933426176", "replie_to": "1065411624419409920", "quoting": null, "text": "Hey @realDonaldTrump, it’s late November.  Think first", "user_id": "76356954", "user_screen_name": "SpshlD", "user_name": "David T", "created_at": 1542910646000.0, "retweets": 0, "likes": 0, "replies": 0, "response_time": 61746.0}, "1065585549698830337": {"tweet_id": "1065585549698830337", "replie_to": "1065411624419409920", "quoting": null, "text": "", "user_id": "981926636324089856", "user_screen_name": "_memorable2", "user_name": "J̶O̷N̶", "created_at": 1542890367000.0, "retweets": 0, "likes": 0, "replies": 0, "response_time": 41467.0}, "1065562561184190464": {"tweet_id": "1065562561184190464", "replie_to": "1065411624419409920", "quoting": null, "text": "So kind of him to prepare us!", "user_id": "1062457095893716992", "user_screen_name": "threalrebeccaw1", "user_name": "threalrebeccawho", "created_at": 1542884886000.0, "retweets": 0, "likes": 0, "replies": 0, "response_time": 35986.0}, "1065452830444539904": {"tweet_id": "1065452830444539904", "replie_to": "1065411624419409920", "quoting": null, "text": "Good one ", "user_id": "406455088", "user_screen_name": "lor_knibbs", "user_name": "lorraine", "created_at": 1542858724000.0, "retweets": 0, "likes": 0, "replies": 0, "response_time": 9824.0}, "1065439045675712513": {"tweet_id": "1065439045675712513", "replie_to": "1065411624419409920", "quoting": null, "text": "Can you imagine if he was your uncle ? Just bought your book. Loved the on being episode so much. Fresh air!!", "user_id": "802643879682080769", "user_screen_name": "jane_wedekind", "user_name": "mrsjanew", "created_at": 1542855438000.0, "retweets": 0, "likes": 0, "replies": 0, "response_time": 6538.0}, "1065432824180867073": {"tweet_id": "1065432824180867073", "replie_to": "1065411624419409920", "quoting": null, "text": "Lol", "user_id": "27107969", "user_screen_name": "tonykwame", "user_name": "Tony Thompson", "created_at": 1542853954000.0, "retweets": 0, "likes": 0, "replies": 0, "response_time": 5054.0}, "1065429686845607936": {"tweet_id": "1065429686845607936", "replie_to": "1065411624419409920", "quoting": null, "text": "I'm blessed with crazy uncles who are much smarter than Donald Trump!", "user_id": "280597580", "user_screen_name": "hwhee3", "user_name": "Heidi Wheeler", "created_at": 1542853206000.0, "retweets": 0, "likes": 0, "replies": 0, "response_time": 4306.0}, "1065423852400852993": {"tweet_id": "1065423852400852993", "replie_to": "1065411624419409920", "quoting": null, "text": "#understatement", "user_id": "2195312761", "user_screen_name": "margaretmillerG", "user_name": "MargaretMG", "created_at": 1542851815000.0, "retweets": 0, "likes": 0, "replies": 0, "response_time": 2915.0}, "1065420574124429313": {"tweet_id": "1065420574124429313", "replie_to": "1065411624419409920", "quoting": null, "text": "Moron in chief!  I’m going to be enjoying an Friendsgiving and thankful for it ", "user_id": "60930107", "user_screen_name": "paula116", "user_name": "Paula Melillo", "created_at": 1542851034000.0, "retweets": 0, "likes": 0, "replies": 0, "response_time": 2134.0}, "1065414117970911232": {"tweet_id": "1065414117970911232", "replie_to": "1065411624419409920", "quoting": null, "text": "What passes for PSA.", "user_id": "1952968951", "user_screen_name": "lcameron4435", "user_name": "Lance Cameron", "created_at": 1542849494000.0, "retweets": 0, "likes": 0, "replies": 0, "response_time": 594.0}, "1065414067555311616": {"tweet_id": "1065414067555311616", "replie_to": "1065411624419409920", "quoting": null, "text": "Our president is an idiot.", "user_id": "827278237814231040", "user_screen_name": "wallish_m", "user_name": "Jeffrey M Wallish", "created_at": 1542849482000.0, "retweets": 0, "likes": 0, "replies": 0, "response_time": 582.0}, "1065411962648051712": {"tweet_id": "1065411962648051712", "replie_to": "1065411624419409920", "quoting": null, "text": "Thanks for the weather report, now keep your ignorant comments to yourself.", "user_id": "786364115899908096", "user_screen_name": "vv_1BlueLiberal", "user_name": "Victoria", "created_at": 1542848980000.0, "retweets": 0, "likes": 0, "replies": 0, "response_time": 80.0}, "1065420666286034945": {"tweet_id": "1065420666286034945", "replie_to": "1065413270281117702", "quoting": null, "text": "Omg that’s amazing", "user_id": "24889586", "user_screen_name": "AnandWrites", "user_name": "Anand Giridharadas", "created_at": 1542851056000.0, "retweets": 0, "likes": 0, "replies": 1, "response_time": 1764.0}, "1065422373883543552": {"tweet_id": "1065422373883543552", "replie_to": "1065412164280877056", "quoting": null, "text": "Is it bad that I’m glad that I’m not spending the holiday with my Trump-loving dad & his wife???", "user_id": "21945393", "user_screen_name": "KateCounter", "user_name": "Kate ☘️", "created_at": 1542851463000.0, "retweets": 0, "likes": 1, "replies": 0, "response_time": 2434.0}, "1065435497344966656": {"tweet_id": "1065435497344966656", "replie_to": "1065420666286034945", "quoting": null, "text": "No, your book is amazing. The story was predicting the predictable.", "user_id": "11179192", "user_screen_name": "jswatz", "user_name": "John Schwartz", "created_at": 1542854592000.0, "retweets": 0, "likes": 1, "replies": 0, "response_time": 3536.0}}