{"946621010949705729": {"tweet_id": "946621010949705729", "replie_to": null, "quoting": "946531657229701120", "text": "Today, I walked in a STRAIGHT LINE to the grocery store. Perhaps I could have used some of that curvature of the Earth that our Country, but not other countries, was going to pay TRILLIONS OF DOLLARS for, to make my walk more exciting. Be careful, and walk straight everybody!https://twitter.com/realdonaldtrump/status/946531657229701120 …", "user_id": "1404297318", "user_screen_name": "j_e_t_b", "user_name": "Jordan Baldridge", "created_at": 1514527011000.0, "retweets": 6, "likes": 33, "replies": 2, "response_time": 0.0}, "946756840221679619": {"tweet_id": "946756840221679619", "replie_to": "946621010949705729", "quoting": null, "text": "He’s not that smart, is he.....?", "user_id": "22512605", "user_screen_name": "andrew_rurik", "user_name": "andrew rurik", "created_at": 1514559395000.0, "retweets": 0, "likes": 0, "replies": 0, "response_time": 32384.0}, "946621772224348160": {"tweet_id": "946621772224348160", "replie_to": "946621010949705729", "quoting": null, "text": "Amazing!", "user_id": "1318913046", "user_screen_name": "TheAtomBaum", "user_name": "Ray-moon-dough", "created_at": 1514527192000.0, "retweets": 0, "likes": 0, "replies": 0, "response_time": 181.0}}