{"946542615108997120": {"tweet_id": "946542615108997120", "replie_to": null, "quoting": "946531657229701120", "text": "but the .. the ... the number of wildfires ... the diminishing arctic sea ice ... the dying of the great barrier reef due to coral bleaching caused by extreme spike in oceanic temperatures ... the rising sea level ... do u rlly think that ... nvmhttps://twitter.com/realdonaldtrump/status/946531657229701120 …", "user_id": "749526583", "user_screen_name": "SidneyMarielle", "user_name": "sidney ♀️", "created_at": 1514508320000.0, "retweets": 15, "likes": 62, "replies": 0, "response_time": 0.0}}