{"1066872000319299586": {"tweet_id": "1066872000319299586", "replie_to": null, "quoting": "1065400254151954432", "text": "yeah!! in your face, democrats! it's cold outside, so global warming & climate change are obviously total shams!! scientists are wrong because our president is ALWAYS right! thank you, trump!!!!! you have saved our nation once again!! https://twitter.com/realDonaldTrump/status/1065400254151954432 …", "user_id": "2457068683", "user_screen_name": "CasterKyle", "user_name": "kiel", "created_at": 1543197081000.0, "retweets": 4, "likes": 18, "replies": 1}, "1067120878167691264": {"tweet_id": "1067120878167691264", "replie_to": "1066872000319299586", "quoting": null, "text": "i love you", "user_id": "2667909158", "user_screen_name": "t_pietrusinski", "user_name": "Teresa Pietrusinski", "created_at": 1543256418000.0, "retweets": 0, "likes": 1, "replies": 1}, "1067150762562781194": {"tweet_id": "1067150762562781194", "replie_to": "1067120878167691264", "quoting": null, "text": "I LOVE YOU ", "user_id": "2457068683", "user_screen_name": "CasterKyle", "user_name": "kiel", "created_at": 1543263543000.0, "retweets": 0, "likes": 0, "replies": 0}}