{"946699496804806656": {"tweet_id": "946699496804806656", "replie_to": null, "quoting": "946531657229701120", "text": "Just when you thought he couldn't get any dumber.https://twitter.com/realdonaldtrump/status/946531657229701120 …", "user_id": "55643029", "user_screen_name": "lorenzofb", "user_name": "Lorenzo Franceschi-Bicchierai", "created_at": 1514545723000.0, "retweets": 5, "likes": 28, "replies": 1, "response_time": 0.0}, "946773497967149056": {"tweet_id": "946773497967149056", "replie_to": "946699496804806656", "quoting": null, "text": "pic.twitter.com/bcbxGfViFj", "user_id": "527313448", "user_screen_name": "0xAmit", "user_name": "Amit Serper", "created_at": 1514563366000.0, "retweets": 0, "likes": 0, "replies": 0, "response_time": 17643.0}}