{"946798795047817216": {"tweet_id": "946798795047817216", "replie_to": null, "quoting": "946531657229701120", "text": "Dear Mr. President - Weather and Climate are NOT the same thing. Chicago and Honolulu could have the same “weather” on any given day, but nobody would confuse their very distinct climates. PLEASE stop sowing scientific confusion among our citizens. It’s morally corrupt.https://twitter.com/realdonaldtrump/status/946531657229701120 …", "user_id": "2372190785", "user_screen_name": "jjtuten", "user_name": "Joyce Tuten", "created_at": 1514569398000.0, "retweets": 19, "likes": 27, "replies": 0, "response_time": 0.0, "sentiment": -0.1791}}